LBL.py
MLE_augmentor.py
RATIO.py
__init__.py
customize_regressor.py
ratio_t2e-0.0.6.dist-info/LICENSE.txt
ratio_t2e-0.0.6.dist-info/METADATA
ratio_t2e-0.0.6.dist-info/WHEEL
ratio_t2e-0.0.6.dist-info/top_level.txt
ratio_t2e-0.0.6.dist-info/RECORD
