Metadata-Version: 2.1
Name: ratio-t2e
Version: 0.0.6
Summary: Linear left barrier loss and data augmention for survival anlysis
Author-email: Oshrit Shtossel <oshritvig@gmail.com>
License: Copyright (c) 2018 The Python Packaging Authority
Keywords: survival,ridge,censored data,ML
Classifier: License :: OSI Approved :: MIT License
Classifier: Programming Language :: Python
Classifier: Programming Language :: Python :: 3
Requires-Python: >=3.7
License-File: LICENSE.txt
Requires-Dist: natsort (>=7.1.1)
Requires-Dist: numpy (>=1.19.2)
Requires-Dist: pandas (>=1.3.4)
Requires-Dist: scikit-learn (==1.1.2)
Requires-Dist: scikit-survival (==0.19.0)
Requires-Dist: scipy (>=1.6.3)
Requires-Dist: six (>=1.15.0)
Requires-Dist: threadpoolctl (>=2.1.0)
Requires-Dist: torch (>=1.11.0)
